redknot/__init__.py
redknot/main.py
redknot-0.0.2.dist-info/licenses/LICENSE
redknot-0.0.2.dist-info/METADATA
redknot-0.0.2.dist-info/WHEEL
redknot-0.0.2.dist-info/entry_points.txt
redknot-0.0.2.dist-info/top_level.txt
redknot-0.0.2.dist-info/RECORD
