Metadata-Version: 2.4
Name: redknot
Version: 0.0.2
Summary: A lightweight dependency graph generator for C and more.
Author-email: Sanyam Asthana <sanyam.asthana@gmail.com>
License-File: LICENSE
Dynamic: license-file
